data_transformation/__init__.py
data_transformation/input.py
data_transformation/transform.py
mjurav_de2_1-0.1.4.dist-info/METADATA
mjurav_de2_1-0.1.4.dist-info/WHEEL
mjurav_de2_1-0.1.4.dist-info/RECORD
