Metadata-Version: 2.1
Name: mjurav-de2-1
Version: 0.1.4
Summary: 
Author: Martynas
Author-email: martynas.j@oxylabs.io
Requires-Python: >=3.11,<3.13
Classifier: Programming Language :: Python :: 3
Classifier: Programming Language :: Python :: 3.11
Requires-Dist: numpy (>=1.26.1,<2.0.0)
Requires-Dist: pydantic (>=2.4.2,<3.0.0)
